odoo/addons/web_group_expand/README.rst
odoo/addons/web_group_expand/__init__.py
odoo/addons/web_group_expand/__manifest__.py
odoo/addons/web_group_expand/i18n/ca.po
odoo/addons/web_group_expand/i18n/es.po
odoo/addons/web_group_expand/i18n/nl.po
odoo/addons/web_group_expand/i18n/pt_BR.po
odoo/addons/web_group_expand/i18n/web_group_expand.pot
odoo/addons/web_group_expand/readme/CONTRIBUTORS.rst
odoo/addons/web_group_expand/readme/DESCRIPTION.rst
odoo/addons/web_group_expand/static/description/icon.png
odoo/addons/web_group_expand/static/description/index.html
odoo/addons/web_group_expand/static/src/js/web_group_expand.js
odoo/addons/web_group_expand/static/src/xml/expand_buttons.xml
odoo/addons/web_group_expand/views/templates.xml
odoo13_addon_web_group_expand-13.0.1.0.1.dev5.dist-info/METADATA
odoo13_addon_web_group_expand-13.0.1.0.1.dev5.dist-info/WHEEL
odoo13_addon_web_group_expand-13.0.1.0.1.dev5.dist-info/top_level.txt
odoo13_addon_web_group_expand-13.0.1.0.1.dev5.dist-info/RECORD
