Metadata-Version: 2.1
Name: odoo13-addon-web-group-expand
Version: 13.0.1.0.1.dev5
Summary: Group Expand Buttons
Home-page: https://github.com/OCA/web
Author: OpenERP SA, AvanzOSC, Serv. Tecnol. Avanzados - Pedro M. Baeza, Therp BV, Xtendoo, Odoo Community Association (OCA)
Author-email: support@odoo-community.org
License: AGPL-3
Platform: UNKNOWN
Classifier: Programming Language :: Python
Classifier: Framework :: Odoo
Classifier: Framework :: Odoo :: 13.0
Classifier: License :: OSI Approved :: GNU Affero General Public License v3
Requires-Python: >=3.5
Requires-Dist: odoo <13.1dev,>=13.0a
